{
  "boundingVolume": {
    "region": [
      0.144383134,
      0.872639556,
      0.144483602,
      0.872739194,
      75.4,
      166.1
    ]
  },
  "geometricError": 0.0,
  "content": {
    "boundingVolume": {
      "region": [
        0.144383134,
        0.872639556,
        0.144483602,
        0.872690753,
        75.4,
        166.1
      ]
    },
    "uri": "15/34274/7281.b3dm"
  },
  "properties": {
    "mittlGebHoehe_rel": {
      "valueType": "STRING",
      "minimum": 0.0,
      "maximum": 22.1
    },
    "usage": {
      "valueType": "STRING"
    },
    "Stadtteil_nr": {
      "valueType": "STRING"
    },
    "yearOfConstruction": {
      "valueType": "INTEGER",
      "minimum": 0,
      "maximum": 0
    },
    "description": {
      "valueType": "STRING"
    },
    "storeyHeightsBelowGround": {
      "valueType": "DOUBLE",
      "minimum": 0.0,
      "maximum": 0.0
    },
    "OTNR": {
      "valueType": "STRING",
      "minimum": 1,
      "maximum": 2
    },
    "Str_schl": {
      "valueType": "STRING"
    },
    "datBearbeitung": {
      "valueType": "STRING"
    },
    "ONR": {
      "valueType": "STRING"
    },
    "measuredHeight": {
      "valueType": "DOUBLE",
      "minimum": 0.0,
      "maximum": 83.5
    },
    "Quality": {
      "valueType": "INTEGER",
      "minimum": 2,
      "maximum": 2
    },
    "function": {
      "valueType": "STRING"
    },
    "mittlGebHoehe_abs": {
      "valueType": "STRING",
      "minimum": 0.0,
      "maximum": 108.01
    },
    "ID": {
      "valueType": "STRING"
    },
    "class": {
      "valueType": "STRING"
    },
    "yearOfDemolition": {
      "valueType": "INTEGER",
      "minimum": 0,
      "maximum": 0
    },
    "hausnr": {
      "valueType": "STRING"
    },
    "storeyHeightsAboveGround": {
      "valueType": "DOUBLE",
      "minimum": 0.0,
      "maximum": 7.0
    },
    "roofType": {
      "valueType": "STRING"
    },
    "Typ": {
      "valueType": "STRING"
    },
    "Bearbeiter": {
      "valueType": "STRING"
    },
    "creationDate": {
      "valueType": "STRING"
    },
    "Bemerkung": {
      "valueType": "STRING"
    },
    "gml:name": {
      "valueType": "STRING"
    },
    "StoreyHeightsAboveGround": {
      "valueType": "STRING",
      "minimum": 1.0,
      "maximum": 4.0
    },
    "Str_name": {
      "valueType": "STRING"
    },
    "Stadtteil_name": {
      "valueType": "STRING"
    },
    "groundHeight": {
      "valueType": "STRING",
      "minimum": 0.0,
      "maximum": 88.06
    },
    "eaveHeight": {
      "valueType": "STRING",
      "minimum": 0.0,
      "maximum": 19.67
    },
    "StoreyHeightsBelowGround": {
      "valueType": "STRING"
    },
    "extLieferant": {
      "valueType": "STRING"
    }
  }
}