[
  {
    "id": "02886f50-7bd5-46d3-a763-974213df3430",
    "name": "Hintergrundkarte Farbe",
    "visibility": false,
    "featureCount": "1",
    "format": "image/png",
    "gfiAttributes": "ignore",
    "gfiTheme": "default",
    "tilesize": 512,
    "transparent": true,
    "transparency": 0,
    "typ": "WMS",
    "layerAttribution": "nicht vorhanden",
    "url": "https://sg.geodatenzentrum.de/wms_topplus_open",
    "version": "1.3.0",
    "layers": "web",
    "legendURL": "",
    "minScale": "0",
    "maxScale": "2500000",
    "supported": [
      "2D",
      "3D"
    ]
  },
  {
    "id": "02886f50-7bd5-46d3-a763-974213df3431",
    "name": "Hintergrundkarte Light Grau",
    "visibility": true,
    "featureCount": "1",
    "format": "image/png",
    "gfiAttributes": "ignore",
    "gfiTheme": "default",
    "tilesize": 512,
    "transparent": true,
    "transparency": 0,
    "typ": "WMS",
    "layerAttribution": "nicht vorhanden",
    "url": "https://sg.geodatenzentrum.de/wms_topplus_open",
    "version": "1.3.0",
    "layers": "web_light_grau",
    "legendURL": "",
    "minScale": "0",
    "maxScale": "2500000",
    "supported": [
      "2D",
      "3D"
    ]
  },
  {
    "id": "02886f50-7bd5-46d3-a763-974213df3439",
    "name": "basemap.de Web Raster Farbe",
    "visibility": false,
    "featureCount": "1",
    "format": "image/png",
    "gfiAttributes": "ignore",
    "gfiTheme": "default",
    "tilesize": 512,
    "transparent": true,
    "transparency": 0,
    "typ": "WMS",
    "layerAttribution": "nicht vorhanden",
    "url": "https://geo.elie.de/geoserver/wms",
    "version": "1.3.0",
    "layers": "guben:de_basemapde_web_raster_farbe",
    "legendURL": "",
    "minScale": "0",
    "maxScale": "2500000",
    "supported": [
      "2D",
      "3D"
    ]
  },
  {
    "id": "r6cn3bn9po5m4y6ru94966sa",
    "name": "Baeume",
    "visibility": true,
    "featureCount": "1",
    "format": "image/png",
    "gfiAttributes": {
      "GATTUNG": "GATTUNG",
      "ST_DURCHM": "ST_DURCHM",
      "POINT_X": "POINT_X",
      "POINT_Y": "POINT_Y",
      "BAUMHOEHE": "BAUMHOEHE"
    },
    "gfiTheme": "default",
    "tilesize": 512,
    "transparent": true,
    "transparency": 0,
    "typ": "WMS",
    "layerAttribution": "nicht vorhanden",
    "url": "https://geo.elie.de/geoserver/wms",
    "version": "1.3.0",
    "layers": "mainz:baeume",
    "legendURL": "",
    "minScale": "0",
    "maxScale": "2500000"
  },
  {
    "id": "r6cn3bn9po5m4y6ru94966sb",
    "name": "Ladestation",
    "visibility": true,
    "featureCount": "1",
    "format": "image/png",
    "gfiAttributes": {
      "FOLIE": "FOLIE",
      "OSCHL": "OSCHL",
      "Erfassung": "Erfassung",
      "Erfasser": "erfasser",
      "PunktNr": "PunktNr",
      "Hoehe": "Hoehe",
      "Text": "Text",
      "Fach_ID": "Fach_ID"
    },
    "gfiTheme": "default",
    "tilesize": 512,
    "transparent": true,
    "transparency": 0,
    "typ": "WMS",
    "layerAttribution": "nicht vorhanden",
    "url": "https://geo.elie.de/geoserver/wms",
    "version": "1.3.0",
    "layers": "mainz:Ladestation",
    "legendURL": "",
    "minScale": "0",
    "maxScale": "2500000"
  },
  {
    "id": "r6cn3bn9po5m4y6ru94966sc",
    "name": "Lampe",
    "visibility": true,
    "featureCount": "1",
    "format": "image/png",
    "gfiAttributes": {
      "OSCHL": "OSCHL",
      "PunktNr": "PunktNr",
      "Hoehe": "Hoehe"
    },
    "gfiTheme": "default",
    "tilesize": 512,
    "transparent": true,
    "transparency": 0,
    "typ": "WMS",
    "layerAttribution": "nicht vorhanden",
    "url": "https://geo.elie.de/geoserver/wms",
    "version": "1.3.0",
    "layers": "mainz:Lampe",
    "legendURL": "",
    "minScale": "0",
    "maxScale": "2500000"
  },
  {
    "id": "r6cn3bn9po5m4y6ru94966sd",
    "name": "Denkmalzone",
    "visibility": true,
    "featureCount": "1",
    "format": "image/png",
    "gfiAttributes": {
      "FOLIE": "FOLIE",
      "OSCHL": "OSCHL",
      "Erfassung": "Erfassung",
      "Erfasser": "erfasser",
      "Text": "Text"
    },
    "gfiTheme": "default",
    "tilesize": 512,
    "transparent": true,
    "transparency": 0,
    "typ": "WMS",
    "layerAttribution": "nicht vorhanden",
    "url": "https://geo.elie.de/geoserver/wms",
    "version": "1.3.0",
    "layers": "mainz:Denkmalzone",
    "legendURL": "",
    "minScale": "0",
    "maxScale": "2500000"
  },
  {
    "id": "r6cn3bn9po5m4y6ru94966se",
    "name": "Behindertenparkplatz",
    "visibility": true,
    "featureCount": "1",
    "format": "image/png",
    "gfiAttributes": {
      "OBJECTID": "OBJECTID"
    },
    "gfiTheme": "default",
    "tilesize": 512,
    "transparent": true,
    "transparency": 0,
    "typ": "WMS",
    "layerAttribution": "nicht vorhanden",
    "url": "https://geo.elie.de/geoserver/wms",
    "version": "1.3.0",
    "layers": "mainz:behinderten_p",
    "legendURL": "",
    "minScale": "0",
    "maxScale": "2500000"
  },
  {
    "id": "r6cn3bn9po5m4y6ru94966sf",
    "name": "Flaechen Themen",
    "visibility": true,
    "featureCount": "1",
    "format": "image/png",
    "gfiAttributes": {
      "OBJECTID": "OBJECTID",
      "art": "art",
      "objname": "objname",
      "Shape_Leng": "Shape_Leng",
      "Shape_Area": "Shape_Area"
    },
    "gfiTheme": "default",
    "tilesize": 512,
    "transparent": true,
    "transparency": 0,
    "typ": "WMS",
    "layerAttribution": "nicht vorhanden",
    "url": "https://geo.elie.de/geoserver/wms",
    "version": "1.3.0",
    "layers": "mainz:flaechen_themen",
    "legendURL": "",
    "minScale": "0",
    "maxScale": "2500000"
  },
  {
    "id": "r6cn3bn9po5m4y6ru94966sg",
    "name": "Lampe ueber Strasse",
    "visibility": true,
    "featureCount": "1",
    "format": "image/png",
    "gfiAttributes": {
      "FOLIE": "FOLIE",
      "OSCHL": "OSCHL",
      "Erfassung": "Erfassung",
      "Erfasser": "erfasser",
      "PunktNr": "PunktNr",
      "Hoehe": "Hoehe",
      "Text": "Text",
      "Fach_ID": "Fach_ID"
    },
    "gfiTheme": "default",
    "tilesize": 512,
    "transparent": true,
    "transparency": 0,
    "typ": "WMS",
    "layerAttribution": "nicht vorhanden",
    "url": "https://geo.elie.de/geoserver/wms",
    "version": "1.3.0",
    "layers": "mainz:lampeueberstrasse",
    "legendURL": "",
    "minScale": "0",
    "maxScale": "2500000"
  },
  {
    "id": "r6cn3bn9po5m4y6ru94966sh",
    "name": "Litfasssaeule",
    "visibility": true,
    "featureCount": "1",
    "format": "image/png",
    "gfiAttributes": {
      "FOLIE": "FOLIE",
      "OSCHL": "OSCHL",
      "Erfassung": "Erfassung",
      "Erfasser": "erfasser",
      "PunktNr": "PunktNr",
      "Hoehe": "Hoehe",
      "Text": "Text",
      "Fach_ID": "Fach_ID"
    },
    "gfiTheme": "default",
    "tilesize": 512,
    "transparent": true,
    "transparency": 0,
    "typ": "WMS",
    "layerAttribution": "nicht vorhanden",
    "url": "https://geo.elie.de/geoserver/wms",
    "version": "1.3.0",
    "layers": "mainz:litfasssaeule",
    "legendURL": "",
    "minScale": "0",
    "maxScale": "2500000"
  },
  {
    "id": "testing123YAYAYA",
    "name": "Tree",
    "visibility": true,
    "typ": "Entities3D",
    "entities": [
      {
        "url": "https://mainz.elie.de/resources/models/beach/high/model.gltf",
        "attributes": {
          "name": "simple building in Planten und Blomen"
        },
        "latitude": 49.997318,
        "longitude": 8.272548,
        "height": 0,
        "heading": 0,
        "pitch": 90,
        "roll": 0,
        "scale": 2,
        "allowPicking": true,
        "show": true
      },
      {
        "url": "https://mainz.elie.de/resources/models/beach/high/model.gltf",
        "attributes": {
          "name": "simple building in Planten und Blomen"
        },
        "latitude": 49.997118,
        "longitude": 8.272272,
        "height": 0,
        "heading": 0,
        "pitch": 90,
        "roll": 0,
        "scale": 2,
        "allowPicking": true,
        "show": true
      },
      {
        "url": "https://mainz.elie.de/resources/models/beach/high/model.gltf",
        "attributes": {
          "name": "simple building in Planten und Blomen"
        },
        "latitude": 49.99708,
        "longitude": 8.27198,
        "height": 0,
        "heading": 0,
        "pitch": 90,
        "roll": 0,
        "scale": 2,
        "allowPicking": true,
        "show": true
      }
    ],
    "gfiAttributes": {
      "name": "Name"
    }
  }
]
