[
  {
    "styleId": "tree",
    "rules": [
      {
        "conditions": {
          "properties": {
            "@Datastreams.0.Observations.0.result": 4
          }
        },
        "style": {
          "legendValue": "Gesundheitszustand - Frost",
          "type": "circle",
          "circleRadius": 8,
          "circleFillColor": [
            139,
            0,
            130,
            0.5
          ],
          "clusterType": "circle",
          "clusterCircleFillColor": [
            139,
            0,
            130,
            0.5
          ],
          "clusterCircleRadius": 10
        }
      },
      {
        "conditions": {
          "properties": {
            "@Datastreams.0.Observations.0.result": 3
          }
        },

        "style": {
          "legendValue": "Gesundheitszustand - Unbekannt",
          "type": "circle",
          "circleRadius": 8,
          "circleFillColor": [
            139,
            139,
            139,
            0.5
          ],
          "clusterType": "circle",
          "clusterCircleFillColor": [
            139,
            255,
            100,
            0.5
          ],
          "clusterCircleRadius": 10
        }
      },
      {
        "conditions": {
          "properties": {
            "@Datastreams.0.Observations.0.result": 2
          }
        },

        "style": {

          "legendValue": "Gesundheitszustand - Trocken",
          "type": "circle",
          "circleRadius": 8,
          "circleFillColor": [
            255,
            20,
            20,
            0.5
          ],
          "clusterType": "circle",
          "clusterCircleFillColor": [
            255,
            20,
            20,
            0.5
          ],
          "clusterCircleRadius": 10
        }
      },
      {
        "conditions": {
          "properties": {
            "@Datastreams.0.Observations.0.result": 1
          }
        },
        "style": {
          "legendValue": "Gesundheitszustand - Trocknet aus",
          "type": "circle",
          "circleRadius": 8,
          "circleFillColor": [
            252,
            186,
            3,
            0.5
          ],
          "clusterType": "circle",
          "clusterCircleFillColor": [
            252,
            186,
            3,
            0.5
          ],
          "clusterCircleRadius": 10
        }
      },
      {
        "conditions": {
          "properties": {
            "@Datastreams.0.Observations.0.result": 0
          }
        },
        "style": {
          "legendValue": "Gesundheitszustand - Gesund",
          "type": "circle",
          "circleRadius": 8,
          "circleFillColor": [
            20,
            255,
            20,
            0.5
          ],
          "clusterType": "circle",
          "clusterCircleFillColor": [
            20,
            255,
            20,
            0.5
          ],
          "clusterCircleRadius": 10
        }
      }
    ]
  },
  {
    "styleId": "parkinglot",
    "rules": [
      {
        "conditions": {
          "properties": {
            "@Datastreams.0.Observations.0.result": false
          }
        },
        "style": {
          "legendValue": "Frei",
          "type": "icon",
          "clusterType": "icon",
          "imageName": "parkinglot_free.svg",
          "imageScale": 0.2,
          "imageOffsetX": 0.5,
          "imageOffsetY": 0.5,
          "clusterImageScale": 0.3
        }
      },
      {
        "conditions": {
          "properties": {
            "@Datastreams.0.Observations.0.result": true
          }
        },
        "style": {
          "legendValue": "Besetzt",
          "type": "icon",
          "clusterType": "icon",
          "imageName": "parkinglot_occupied.svg",
          "imageScale": 0.2,
          "imageOffsetX": 0.5,
          "imageOffsetY": 0.5,
          "clusterImageScale": 0.3
        }
      }
    ]
  },
  {
    "styleId": "new-tree",
    "rules": [
      {
        "style": {
          "type": "circle",
          "circleRadius": 8,
          "circleFillColor": [
            20,
            250,
            20,
            0.5
          ],
          "clusterType": "circle",
          "clusterCircleFillColor": [
            20,
            250,
            20,
            0.5
          ],
          "clusterCircleRadius": 10
        }
      }
    ]
  },
  {
    "styleId": "lampe",
    "rules": [
      {
        "style": {
          "type": "circle",
          "circleRadius": 8,
          "circleFillColor": [
            250,
            20,
            20,
            0.5
          ],
          "clusterType": "circle",
          "clusterCircleFillColor": [
            250,
            20,
            20,
            0.5
          ],
          "clusterCircleRadius": 10
        }
      }
    ]
  },
  {
    "styleId": "litfasssaeule",
    "rules": [
      {
        "style": {
          "type": "circle",
          "circleRadius": 8,
          "circleFillColor": [
            250,
            20,
            250,
            0.5
          ],
          "clusterType": "circle",
          "clusterCircleFillColor": [
            250,
            20,
            250,
            0.5
          ],
          "clusterCircleRadius": 10
        }
      }
    ]
  },
  {
    "styleId": "stellplaetze",
    "rules": [
      {
        "style": {
            "lineStrokeColor": [
              20,20,250,0.5
            ]
        }
      }
    ]
  },

  {
    "styleId": "ladestation",
    "rules": [
      {
        "style": {
          "type": "icon",
          "clusterType": "icon",
          "imageName": "E-Charging-Icon.png",
          "imageScale": 0.07,
          "imageOffsetX": 0.5,
          "imageOffsetY": 0.5,
          "clusterImageScale": 0.1
        }
      }
    ]
  },
  {
    "styleId": "b-parkplatz",
    "rules": [
      {
        "style": {
          "type": "icon",
          "clusterType": "icon",
          "imageName": "Disabled-Icon.png",
          "imageScale": 0.07,
          "imageOffsetX": 0.5,
          "imageOffsetY": 0.5,
          "clusterImageScale": 0.1
        }
      }
    ]
  }
]
